LICENSE
MANIFEST.in
setup.py
Clip2Zeus.egg-info/PKG-INFO
Clip2Zeus.egg-info/SOURCES.txt
Clip2Zeus.egg-info/dependency_links.txt
Clip2Zeus.egg-info/top_level.txt
clip2zeus/__init__.py
clip2zeus/clip2zeus_ctl.py
clip2zeus/clip2zeus_service.py
clip2zeus/common.py
clip2zeus/config.py
clip2zeus/globals.py
clip2zeus/gui.py
clip2zeus/linux.py
clip2zeus/main.py
clip2zeus/osx.py
clip2zeus/win32.py
clip2zeus/scripts/clip2zeus
clip2zeus/scripts/clip2zeusctl
clip2zeus/scripts/tkclip2zeus