Metadata-Version: 1.0
Name: Clip2Zeus
Version: 1.2a
Summary: Monitor your clipboard for URLs and automatically shorten them using 2Zeus
Home-page: http://www.codekoala.com/
Author: Josh VanderLinden
Author-email: codekoala at gmail com
License: MIT
Keywords: url-shortening,utilities
Platform: Windows
Platform: OSX
Platform: Linux
Classifier: Development Status :: 4 - Beta
Classifier: Environment :: Console
Classifier: Environment :: MacOS X
Classifier: Environment :: Win32 (MS Windows)
Classifier: Environment :: X11 Applications :: GTK
Classifier: Intended Audience :: End Users/Desktop
Classifier: Intended Audience :: Information Technology
Classifier: License :: OSI Approved :: MIT License
Classifier: Operating System :: MacOS :: MacOS X
Classifier: Operating System :: Microsoft :: Windows :: Windows NT/2000
Classifier: Operating System :: POSIX :: Linux
Classifier: Programming Language :: Python
Classifier: Topic :: Communications :: Chat
Classifier: Topic :: Internet
Classifier: Topic :: Utilities
